{
  "parent": "minecraft:recipes/root",
  "criteria": {
    "has_stripped_empty_coconut": {
      "conditions": {
        "items": [
          {
            "items": "blocksforbuilders:stripped_empty_coconut"
          }
        ]
      },
      "trigger": "minecraft:inventory_changed"
    },
    "has_the_recipe": {
      "conditions": {
        "recipe": "blocksforbuilders:scorchwood_sapling_from_smelting_stripped_empty_coconut"
      },
      "trigger": "minecraft:recipe_unlocked"
    }
  },
  "requirements": [
    [
      "has_the_recipe",
      "has_stripped_empty_coconut"
    ]
  ],
  "rewards": {
    "recipes": [
      "blocksforbuilders:scorchwood_sapling_from_smelting_stripped_empty_coconut"
    ]
  }
}